odoo8_addon_web_decimal_numpad_dot-8.0.1.0.0.99.dev2-py2.7-nspkg.pth
odoo8_addon_web_decimal_numpad_dot-8.0.1.0.0.99.dev2.dist-info/METADATA
odoo8_addon_web_decimal_numpad_dot-8.0.1.0.0.99.dev2.dist-info/RECORD
odoo8_addon_web_decimal_numpad_dot-8.0.1.0.0.99.dev2.dist-info/WHEEL
odoo8_addon_web_decimal_numpad_dot-8.0.1.0.0.99.dev2.dist-info/namespace_packages.txt
odoo8_addon_web_decimal_numpad_dot-8.0.1.0.0.99.dev2.dist-info/top_level.txt
odoo_addons/web_decimal_numpad_dot/README.rst
odoo_addons/web_decimal_numpad_dot/__init__.py
odoo_addons/web_decimal_numpad_dot/__openerp__.py
odoo_addons/web_decimal_numpad_dot/i18n/web_decimal_numpad_dot.pot
odoo_addons/web_decimal_numpad_dot/static/description/icon.png
odoo_addons/web_decimal_numpad_dot/static/src/js/numpad_dot.js
odoo_addons/web_decimal_numpad_dot/views/web_decimal_numpad_dot.xml
